README.md
main.py
setup.py
PyLib/Controller.py
PyLib/MainUi.py
PyLib/Module-Test.py
PyLib/ProgramManagement.py
PyLib/__init__.py
PyQt5_comet.egg-info/PKG-INFO
PyQt5_comet.egg-info/SOURCES.txt
PyQt5_comet.egg-info/dependency_links.txt
PyQt5_comet.egg-info/top_level.txt