Metadata-Version: 2.1
Name: PyQt5-comet
Version: 1.0.1
Summary: PyQt5开发框架
Home-page: https://github.com/SkyBlueEternal/PyQt5-comet
Author: 柠檬菠萝
Author-email: white.mi@yahoo.com
License: GNU General Public License v3.0
Platform: UNKNOWN
Requires-Python: >=3.7
